OpticsLab/__init__.py
OpticsLab/components.py
OpticsLab/grid.py
OpticsLab/monitor.py
OpticsLab/source.py
OpticsLab-0.0.0.dist-info/LICENSE
OpticsLab-0.0.0.dist-info/METADATA
OpticsLab-0.0.0.dist-info/WHEEL
OpticsLab-0.0.0.dist-info/top_level.txt
OpticsLab-0.0.0.dist-info/RECORD
